HISTORY.rst
LICENSE
MANIFEST.in
README.rst
setup.cfg
setup.py
mr.bob2.egg-info/PKG-INFO
mr.bob2.egg-info/SOURCES.txt
mr.bob2.egg-info/dependency_links.txt
mr.bob2.egg-info/entry_points.txt
mr.bob2.egg-info/not-zip-safe
mr.bob2.egg-info/requires.txt
mr.bob2.egg-info/top_level.txt
mrbob/__init__.py
mrbob/bobexceptions.py
mrbob/cli.py
mrbob/configurator.py
mrbob/hooks.py
mrbob/parsing.py
mrbob/rendering.py
mrbob/docs/Makefile
mrbob/docs/source/api.rst
mrbob/docs/source/conf.py
mrbob/docs/source/developer.rst
mrbob/docs/source/index.rst
mrbob/docs/source/mr.bob_flow.jpg
mrbob/docs/source/mr.bob_flow.xml
mrbob/docs/source/other.rst
mrbob/docs/source/templateauthor.rst
mrbob/docs/source/userguide.rst
mrbob/template_sample/.mrbob.ini
mrbob/template_sample/sample.txt.bob
mrbob/template_starter/.mrbob.ini
mrbob/template_starter/sample.txt.bob