Metadata-Version: 1.1
Name: mr.bob2
Version: 0.2.3
Summary: Bob renders directory structure templates
Home-page: https://github.com/iElectric/mr.bob.git
Author: Domen Kozar, Tom Lazar
Author-email: UNKNOWN
License: BSD
Platform: UNKNOWN
Classifier: Programming Language :: Python
Classifier: Programming Language :: Python :: Implementation :: CPython
Classifier: Programming Language :: Python :: Implementation :: PyPy
Classifier: Programming Language :: Python :: 2.6
Classifier: Programming Language :: Python :: 2.7
Classifier: Programming Language :: Python :: 3
Classifier: Programming Language :: Python :: 3.2
Classifier: Programming Language :: Python :: 3.3
Classifier: Programming Language :: Python :: 3.4
